Workbook

Sheet 研发过程节点
A2: 阶段 | B2: 主要工作 | C2: 需要提供 | D2: 阶段输出/通过条件 | E2: 备注
A3: 1. 资料准备 | B3: 收集、分类、脱敏和整理项目资料 | C3: 国标及行业标准文档、专家经验文档资料、典型CAD图、已知问题及正确答案 | D3: 资料清单、规则清单、样本图纸集、标注口径 | E3: 典型CAD图 不需要准备太齐 有个 几十张即可 用于验证实验； 国标及行业标准文档、专家经验文档资料 这些要尽可能全面，可以不断的补齐；
A4: 2. 能力验证 | B4: 申请OCR视觉大模型，推理大模型模型接入 用真实图纸测试识别和判断能力 | C4: 10～20张有代表性的图纸，并由专家确认正确答案 ，提供图纸复杂程度：低/中/高各3至5张，每个图纸给出标准图 和 已知错图，来验证能力 | D4: 验证报告：识别准确度 百分比；哪些能识别、哪些不能识别、漏检误报情况、单图成本和处理时间 | E4: 能力验证至少要回答以下问题： • PDF中的文字、尺寸、公差和符号能否可靠提取。 • OCR结果能否与图纸位置、尺寸线和几何对象对应。 • 国标条款和专家规则能否转成可执行检查规则。 • 模型能否指出问题位置，并提供正确依据。 • 漏检率、误报率和人工复核时间是否可以接受。 • 单张图纸的API费用和处理时间是否可控。 • DWG/DXF是否只作为辅助输入，还是必须实现结构化解析
A5: 3. 产品原型 | B5: 把已验证能力串成最小闭环 | C5: 双方参与确认结果展示方式 | D5: 上传图纸→识别→规则检查→问题定位→输出依据和建议的可操作原型
A6: 4. 产品设计与研发 | B6: 完成正式功能、数据结构、规则管理和稳定性建设、基础设施、基础服务搭建 | C6: 持续确认规则、界面和业务流程 | D6: 第一阶段可用产品，包括PDF处理、OCR、规则引擎、模型审校、报告和管理界面
A7: 5. 演示与交付 | B7: 部署演示环境、准备演示案例、修复演示问题并培训 | C7: 确认演示图纸和验收场景 | D7: 可部署版本、操作文档、测试报告、演示及培训
A8: 6. 试用阶段 | B8: 试用阶段License许可，使用真实图纸运行，记录问题并进行有限优化 | C8: 真实试用图纸、专家反馈和问题确认 | D8: 试用报告、问题清单、第一阶段验收结论及后续优化范围

Sheet 第一阶段内容
A2: 一、阶段目标
B3: 第一阶段建设一个可实际试用的CAD图纸规范检查产品。
B4: 系统接收客户图纸后，依据国标、行业规范和专家经验，自动发现可能不规范的内容，并输出：
B5: 问题所在页和图纸位置。
B6: 涉及的尺寸、符号、文字或图形对象。
B7: 问题类型和严重程度。
B8: 对应的国标条款或专家规则。
B9: 判断依据和修改建议。
B10: 无法确定时明确标记“需要专家复核”。
B11: 输入以PDF图纸为主，DWG/DXF作为补充输入。
B13: 第一阶段不包含学生图纸评分。第二阶段将在第一阶段的识别、规则检查和证据定位能力上继续建设评分功能。
A14: 二、实施流程 | B14: 资料准备
B15: → 能力验证
B16: → 产品原型
B17: → 产品设计与研发
B18: → 演示交付
B19: → 客户试用与验收
A55: 第一阶段产出物 | B55: 第一阶段产品及部署包。
B56: PDF图纸识别和规范检查功能。
B57: DWG/DXF辅助接入能力。
B58: 国标及专家规则知识库。
B59: 识图服务能力
B60: 网关等基础设施
B61: 问题定位、依据和建议展示。
B62: 结构化检查结果及报告。
B63: 客户、用户和License管理功能。
B64: API用量、图纸额度及操作记录。
B65: 能力验证报告。
B66: POC测试报告。
B67: 部署及操作说明。
... B69: 客户试用及验收记录。
A71: 阶段边界 | B71: 第一阶段不包含：
B72: 学生图纸自动评分。
B73: 标准答案图纸比对评分。
B74: 本地大模型训练。
B75: GPU服务器采购。
B76: 无限制图纸类型支持。
B77: 无期限免费试用和维护。

Sheet 单价依据与范围
B2: 单价解释与第一阶段交付范围
B3: 将“市场公开费率”“文档预算值”“新增规划假设”分开说明，避免将假设当作报价。
B5: 成本项目 | C5: 依据类型 | D5: 为什么采用这个单价 / 如何计算 | E5: 需要确认的事项
B6: 工程师月成本 | C6: 内部预算值 | D6: 25,000元/人月，按20个工作日折合1,250元/人日；4个月约80人日。
B7: Mistral OCR 4 | C7: 官方费率＋用量假设 | D7: 开发与演示预计1,100页次，实际约31.68元；预算按100元取整。 | E7: OCR页数、页面比例和重试率需样本实测。
B8: GPT-5.6 Sol | C8: 官方费率＋用量假设 | D8: 图像、文字输入和计费输出约11,107.70元；预算按11,200元计。 | E8: 50K文字输入、4K计费输出及8轮回归需实测校准。
B9: GPT-6 Astra | C9: 官方费率＋用量假设 | D9: 审校调用约20,641.26元；分配20,600元，使模型API预算合计31,900元。 | E9: 30K文字输入、4K计费输出及100%审校覆盖率需实测。
B10: 技术尽调验证 | C10: 包含费用 | D10: 签前选10张客户真实图纸验证OCR、视觉分析、规则和审校链路；工程工时已含人力。 | E10: 客户需提供可代表真实难度的图纸及预期问题。
B11: 国内ECS实例 | C11: 公开价格参考＋预算预留 | D11: 4核16G计算资源约400元/月，系统盘约50元/月，合计450元/月×12。 | E11: 云厂商、地域、磁盘性能及优惠以采购订单为准。
B12: 国内公网带宽 | C12: 预算预留 | D12: 按150元/月×12个月预算，用于客户远程访问演示系统。 | E12: 带宽大小和计费方式需根据并发与地域询价。
B13: 对象存储OSS | C13: 预算预留 | D13: 原图、切片和结果JSON存储及少量外网流量，合计500元/年。 | E13: 容量、留存周期、请求次数和外网流量尚未实测。
B14: 域名＋HTTPS证书 | C14: 预算预留 | D14: 域名和HTTPS证书合计300元/年。 | E14: 可使用免费证书；域名后缀和续费价格待确认。
B15: 云监控／日志／CI | C15: 预算预留 | D15: 告警、日志及持续集成流水线合计1,200元/年。 | E15: 日志量、留存时间和流水线分钟数待确认。
B16: 海外网关节点 | C16: 文档预算值 | D16: 稳定接入节点及流量1,500元/月×12个月；不重复计模型消费。 | E16: 真实接入方案、合规边界、流量和服务保障需确认。
B17: 国标文本资料 | C17: 客户提供 | D17: 客户提供所需国标文本，研发费用0元；30份为资料数量占位。 | E17: 资料版本、范围及可用性由双方确认；工程转录实现仍包含在人力成本中。
B18: 标准条款结构化 | C18: 客户专家支持＋包含费用 | D18: 客户机械顾问确定条款范围；研发结构化和工程实现已含研发人力。 | E18: 先冻结标准清单、条款范围和适用条件。
... B37: 验收 | C37: 专家标注＋留出测试 | D37: 误报、漏检、定位、依据准确性和人工复核时间 | E37: 20张独立测试集适合POC，不代表通用可靠性证明。
B40: 模型适用性 | C40: GPT-6 Astra支持图像、结构化输出与工具调用，可承担审校；实际效果待测试。
B41: 阶段边界 | C41: 不含学生评分、本地模型训练、GPU采购与对外多租户模型服务。
B42: API价格 | C42: 标准API按量计费；ChatGPT订阅不计作此项目API额度。
B43: 参考资料 | C43: https://developers.openai.com/api/docs/models/gpt-6-astra
B45: 服务器价格参考 | C45: https://buy.cloud.tencent.com/pricing/cvm/calculator?devPayMode=monthly&imageType=linux
B46: 服务器预算口径 | C46: 2026-09-17公开价格检索参考；计算、系统盘和公网带宽为预算拆分，非锁定报价。

Sheet API参数
B2: API 价格与工作量参数
B3: 核验日期：2026-09-17；标准同步API，无缓存折扣；黄色蓝字可修改。
B5: 参数 | C5: 数值 | D5: 单位 | F5: 用途及计费口径 | H5: 来源 / 假设
B6: 预算汇率 | C6: 7.2 | D6: 人民币/美元 | F6: 仅为预算汇率，可按实际结算调整。 | H6: 预算假设
B7: Mistral OCR 4.0 | C7: 4 | D7: 美元/千页 | F7: 普通OCR端点，不使用收费自定义文档注释。 | H7: https://docs.mistral.ai/models/ocr-4-0
B8: GPT-5.6 Sol 输入 | C8: 4 | D8: 美元/百万token | F8: 图像和文字输入均按输入单价计费。 | H8: https://developers.openai.com/api/docs/pricing
B9: GPT-5.6 Sol 输出 | C9: 20 | D9: 美元/百万token | F9: 输出包括计费思考token。 | H9: https://developers.openai.com/api/docs/pricing
B10: GPT-6 Astra 输入 | C10: 10 | D10: 美元/百万token | F10: 用于最终审校；文字和图像输入采用同一输入单价。 | H10: https://developers.openai.com/api/docs/pricing
B11: GPT-6 Astra 输出 | C11: 50 | D11: 美元/百万token | F11: 输出包括计费思考token。 | H11: https://developers.openai.com/api/docs/pricing
B12: 长上下文阈值 | C12: 272000 | D12: 输入token/请求 | F12: 每请求文字＋图像输入合计超过此值，提高整次请求费率。 | H12: https://developers.openai.com/api/docs/pricing
B13: 长上下文输入倍率 | C13: 2 | D13: 倍 | F13: 输入超过阈值时，输入费率乘此倍数。 | H13: https://developers.openai.com/api/docs/pricing
B14: 长上下文输出倍率 | C14: 1.5 | D14: 倍 | F14: 输入超过阈值时，输出费率乘此倍数。 | H14: https://developers.openai.com/api/docs/pricing
B15: 图像计费token倍率 | C15: 1.2 | D15: 倍 | F15: 有效patch数乘倍率后向上取整；只乘一次。 | H15: https://developers.openai.com/api/docs/guides/images-vision
B16: 整页图有效patch数 | C16: 2500 | D16: patch/图 | F16: 2048×2048方形整页画布，high细节；缩放后50×50个patch。 | H16: https://developers.openai.com/api/docs/guides/images-vision
B17: 局部图有效patch数 | C17: 1024 | D17: patch/图 | F17: 1024×1024局部裁剪，high细节；32×32个patch。 | H17: https://developers.openai.com/api/docs/guides/images-vision
... B34: Astra每请求计费输出 | C34: 4000 | D34: token | F34: 含审校报告和思考token。 | H34: 用量假设，待实测
B37: 模型费用 | F37: API独立按量计费，不能用ChatGPT订阅价格替代。
B38: 图像精度 | F38: 图像规格用于计费预算，不证明细小尺寸、公差和符号已经能准确识别。
B39: 避免重复输入 | F39: 本地渲染PDF后传图，不再重复上传同一PDF作为模型文件输入。
B40: 工具费用 | F40: 规则计算、检索和渲染使用项目服务器；不启用收费搜索或代码容器。
B42: 文字输入如何估 | F42: 50K/30K是复杂图纸连同规则上下文的占位预算；用真实usage校准。
B43: 输出如何估 | F43: 4K为每次请求全部计费输出假设；高推理强度可能明显增加。

Sheet API测算
B2: OCR、图像识别与审校 API 测算
B3: Mistral OCR 4.0 → GPT-5.6 Sol视觉分析 → 规则检查 → GPT-6 Astra审校。
B7: 调用项目 | C7: 计价单位 | D7: 单价（美元） | E7: 开发用量 | F7: 开发费用（元） | G7: 演示用量 | H7: 演示费用（元） | J7: 计费说明
B8: Mistral OCR 4.0 | C8: 千页 | D8: =API参数!C7 -> 4 | E8: =D23 -> 550 | F8: =E8/1000*D8*1*API参数!$C$6 -> 15.84 | G8: =F23 -> 550 | H8: =G8/1000*D8*1*API参数!$C$6 -> 15.84 | J8: 用量为页次，除以1000再乘单价及汇率。
B9: Sol图像输入 | C9: 百万token | D9: =API参数!C8 -> 4 | E9: =D21*D34 -> 34830400 | F9: =E9/1000000*D9*$G$34*API参数!$C$6 -> 1003.1155 | G9: =F21*D34 -> 4353800 | H9: =G9/1000000*D9*$G$34*API参数!$C$6 -> 125.38944 | J9: 整页＋局部图的图像token，按输入价计费。
B10: Sol文字输入 | C10: 百万token | D10: =API参数!C8 -> 4 | E10: =D21*C34 -> 220000000 | F10: =E10/1000000*D10*$G$34*API参数!$C$6 -> 6336 | G10: =F21*C34 -> 27500000 | H10: =G10/1000000*D10*$G$34*API参数!$C$6 -> 792 | J10: OCR文字、规则和上下文；不含图像token。
B11: Sol计费输出 | C11: 百万token | D11: =API参数!C9 -> 20 | E11: =D21*F34 -> 17600000 | F11: =E11/1000000*D11*$H$34*API参数!$C$6 -> 2534.4 | G11: =F21*F34 -> 2200000 | H11: =G11/1000000*D11*$H$34*API参数!$C$6 -> 316.8 | J11: 视觉分析和候选问题输出，包含思考token。
B12: Astra图像输入 | C12: 百万token | D12: =API参数!C10 -> 10 | E12: =D22*D35 -> 34830400 | F12: =E12/1000000*D12*$G$35*API参数!$C$6 -> 2507.7888 | G12: =F22*D35 -> 4353800 | H12: =G12/1000000*D12*$G$35*API参数!$C$6 -> 313.4736 | J12: 审校重新看图，是第二个请求的图像输入费用。
B13: Astra文字输入 | C13: 百万token | D13: =API参数!C10 -> 10 | E13: =D22*C35 -> 132000000 | F13: =E13/1000000*D13*$G$35*API参数!$C$6 -> 9504 | G13: =F22*C35 -> 16500000 | H13: =G13/1000000*D13*$G$35*API参数!$C$6 -> 1188 | J13: 候选问题、规则依据、证据文字及审校指令。
B14: Astra计费输出 | C14: 百万token | D14: =API参数!C11 -> 50 | E14: =D22*F35 -> 17600000 | F14: =E14/1000000*D14*$H$35*API参数!$C$6 -> 6336 | G14: =F22*F35 -> 2200000 | H14: =G14/1000000*D14*$H$35*API参数!$C$6 -> 792 | J14: 最终审校及报告，包含思考token。
B15: API预计消耗 | F15: =IF(COUNT(API参数!C6:C34)<29,NA(),SUM(F8:F14)) -> 28237.144 | H15: =IF(COUNT(API参数!C6:C34)<29,NA(),SUM(H8:H14)) -> 3543.503 | J15: 含重试预留；七项相加即该阶段全部API费用。
B16: 预算取整单位（元） | D16: 100
B17: 纳入项目预算 | F17: =ROUNDUP(F15/D16,0)*D16 -> 28300 | H17: =ROUNDUP(H15/D16,0)*D16 -> 3600 | J17: 分别向上取整到100元；不再另计一笔模型充值预算。
B20: 调用量计算 | C20: 单位 | D20: 开发数量 | E20: 说明 | F20: 演示数量
B21: Sol请求次数 | C21: 次 | D21: =API参数!C21*API参数!C22*API参数!C23*(1+API参数!C29) -> 4400 | F21: =API参数!C25*API参数!C26*API参数!C27*(1+API参数!C29) -> 550 | J21: 图纸张数×平均页数×推理轮数×（1＋额外重试率）。
B22: Astra请求次数 | C22: 次 | D22: =D21*API参数!C30 -> 4400 | F22: =F21*API参数!C30 -> 550 | J22: Sol请求数×审校覆盖率。
B23: OCR处理页数 | C23: 页次 | D23: =API参数!C21*API参数!C22*API参数!C24*API参数!C20*(1+API参数!C29) -> 550 | F23: =API参数!C25*API参数!C26*API参数!C28*API参数!C20*(1+API参数!C29) -> 550 | J23: 张数×平均页数×OCR轮数×OCR覆盖率×（1＋额外重试率）。
B27: 图像类型 | C27: 有效patch | D27: 计费倍率 | E27: 每图token | F27: 每页图数 | G27: 每页图像token
B28: 整页图 high | C28: =API参数!C16 -> 2500 | D28: =API参数!C15 -> 1.2 | E28: =ROUNDUP(C28*D28,0) -> 3000 | F28: =API参数!C18 -> 1 | G28: =E28*F28 -> 3000
B29: 局部裁剪 high | C29: =API参数!C17 -> 1024 | D29: =API参数!C15 -> 1.2 | E29: =ROUNDUP(C29*D29,0) -> 1229 | F29: =API参数!C19 -> 4 | G29: =E29*F29 -> 4916
B30: 每请求图像token | G30: =SUM(G28:G29) -> 7916 | J30: 每请求处理1页；图像token＝各类图像数量×每图token之和。
B33: 模型 | C33: 文字输入token | D33: 图像输入token | E33: 总输入token | F33: 计费输出token | G33: 输入倍率 | H33: 输出倍率
B34: GPT-5.6 Sol | C34: =API参数!C31 -> 50000 | D34: =$G$30 -> 7916 | E34: =SUM(C34:D34) -> 57916 | F34: =API参数!C32 -> 4000 | G34: =IF(E34>API参数!$C$12,API参数!$C$13,1) -> 1 | H34: =IF(E34>API参数!$C$12,API参数!$C$14,1) -> 1
B35: GPT-6 Astra | C35: =API参数!C33 -> 30000 | D35: =$G$30 -> 7916 | E35: =SUM(C35:D35) -> 37916 | F35: =API参数!C34 -> 4000 | G35: =IF(E35>API参数!$C$12,API参数!$C$13,1) -> 1 | H35: =IF(E35>API参数!$C$12,API参数!$C$14,1) -> 1
B39: 单次费用推导 | C39: 计价单位 | D39: 单价（美元） | E39: 单次用量 | F39: 单次费用（元）
B40: =B8 -> Mistral OCR 4.0 | C40: =C8 -> 千页 | D40: =D8 -> 4 | E40: =1 -> 1 | F40: =E40/1000*D40*1*API参数!$C$6 -> 0.0288 | J40: OCR：每页÷1000×4美元×汇率。
B41: =B9 -> Sol图像输入 | C41: =C9 -> 百万token | D41: =D9 -> 4 | E41: =D34 -> 7916 | F41: =E41/1000000*D41*$G$34*API参数!$C$6 -> 0.2279808 | J41: 图像输入：图像token÷100万×输入单价×汇率。
B42: =B10 -> Sol文字输入 | C42: =C10 -> 百万token | D42: =D10 -> 4 | E42: =C34 -> 50000 | F42: =E42/1000000*D42*$G$34*API参数!$C$6 -> 1.44 | J42: 文字输入：文字token÷100万×输入单价×汇率。
B43: =B11 -> Sol计费输出 | C43: =C11 -> 百万token | D43: =D11 -> 20 | E43: =F34 -> 4000 | F43: =E43/1000000*D43*$H$34*API参数!$C$6 -> 0.576 | J43: 输出：计费输出token÷100万×输出单价×汇率。
B44: =B12 -> Astra图像输入 | C44: =C12 -> 百万token | D44: =D12 -> 10 | E44: =D35 -> 7916 | F44: =E44/1000000*D44*$G$35*API参数!$C$6 -> 0.569952 | J44: Astra按自身输入单价计算，传入相同的图像证据。
B45: =B13 -> Astra文字输入 | C45: =C13 -> 百万token | D45: =D13 -> 10 | E45: =C35 -> 30000 | F45: =E45/1000000*D45*$G$35*API参数!$C$6 -> 2.16 | J45: Astra文字输入量与Sol独立设置。
B46: =B14 -> Astra计费输出 | C46: =C14 -> 百万token | D46: =D14 -> 50 | E46: =F35 -> 4000 | F46: =E46/1000000*D46*$H$35*API参数!$C$6 -> 1.44 | J46: Astra输出按50美元/百万token计算，含思考token。
B47: 单页完整链路费用 | F47: =SUM(F40:F46) -> 6.4427328 | J47: 单页1次OCR＋1次Sol＋1次Astra，不含重试；复核覆盖率改变不修改此单次定义。
B50: 计费注意 | J50: OCR缓存由应用实现；未计提示词缓存、Batch优惠或收费工具。

Sheet 费用总表
B2: CAD 第一阶段研发成本估算
B3: 单图规范检查；4个月研发交付，基础设施按1年计。
B5: 类别 | C5: 细项 | D5: 计费口径与说明 | E5: 金额（¥）
B6: 人力 | C6: 全栈工程师 × 1 | D6: 4个月（3个月开发测试＋1个月演示试跑），25,000元/人月 | E6: =成本预算!G7 -> 100000
B7: 模型API | C7: Mistral OCR 4 | D7: 开发与演示共1,100页次，实际约31.68元；预算按100元取整 | E7: =成本预算!G8 -> 100
C8: GPT-5.6 Sol | D8: 视觉分析调用预算；50K文字输入＋7,916图像token＋4K计费输出 | E8: =成本预算!G9 -> 11200
C9: GPT-6 Astra | D9: 复杂问题审校预算；30K文字输入＋7,916图像token＋4K计费输出 | E9: =成本预算!G10 -> 20600
C10: 技术尽调验证 | D10: 签前用10张客户真实图纸验证OCR→Sol→规则→Astra链路；已含人力 | E10: =成本预算!G11 -> 0
B11: 基础设施 | C11: 国内ECS实例 | D11: 1台4核16G，计算资源约400＋系统盘约50＝450元/月 × 12个月 | E11: =成本预算!G12 -> 5400
C12: 国内公网带宽 | D12: 150元/月 × 12个月，用于客户远程访问演示系统 | E12: =成本预算!G13 -> 1800
C13: 对象存储OSS | D13: 原图、切片、结果JSON存储及少量外网流量预留 | E13: =成本预算!G14 -> 500
C14: 域名＋HTTPS证书 | D14: 一年 | E14: =成本预算!G15 -> 300
C15: 云监控／日志／CI | D15: 告警、日志和持续集成流水线，一年 | E15: =成本预算!G16 -> 1200
C16: 海外网关节点 | D16: 稳定接入节点及流量，1,500元/月 × 12个月 | E16: =成本预算!G17 -> 18000
B17: 知识库 | C17: 国标文本资料 | D17: 客户提供所需标准资料，研发费用0元。 | E17: =成本预算!G18 -> 0
C18: 标准条款结构化 | D18: 客户机械顾问确定条款范围；研发结构化和工程实现已含研发人力。 | E18: =成本预算!G19 -> 0
C19: 专家规则转写 | D19: 客户专家提供并审核规则；研发转录开发已含研发人力。 | E19: =成本预算!G20 -> 0
C20: 向量库／图谱工具 | D20: 开源部署，无额外软件授权费用，开发已含人力 | E20: =成本预算!G21 -> 0
B21: 数据准备 | C21: 图纸样本收集 | D21: 客户收集、清理并提供典型图纸；研发费用0元。 | E21: =成本预算!G22 -> 0
C22: 开发期人工标注 | D22: 客户专家承担开发集标注与复核；属于客户承担的专家支持费用，研发费用0元。 | E22: =成本预算!G23 -> 0
C23: 演示期补充标注 | D23: 客户专家承担演示样本补充标注与复核；属于客户承担的专家支持费用，研发费用0元。 | E23: =成本预算!G24 -> 0
C24: 独立测试集标注 | D24: 客户专家独立完成测试集标注与复核；属于客户承担的专家支持费用，研发费用0元。 | E24: =成本预算!G25 -> 0
B25: 测评 | C25: 评估脚本／POC测试报告 | D25: 已含人力 | E25: =成本预算!G26 -> 0
B26: 其他 | C26: 差旅、税费、不可预见 | D26: 按研发直接费用小计的5%计提。 | E26: =成本预算!G29 -> 7955
B27: 总计 | D27: 第一阶段内部成本预算，非含税销售报价 | E27: =成本预算!G30 -> 167055
B30: 计费解释 | D30: 逐项单价依据见“单价依据与范围”；图像、OCR和模型token推导见“API测算”。
B31: 用量口径 | D31: 开发500张×1页×8轮；演示500张×1页×1轮。OCR各执行1轮并缓存。
B32: 待确认增项 | D32: 客户承担的专家支持费用不计入研发费用；CAD工具授权预留5,000元未计入总计。
B33: 估算说明 | D33: 类别和细项按客户提供的CSV整理；金额采用本次已确认口径。

Sheet 成本预算
B1: CAD 第一阶段研发成本预算
B2: 4个月研发与交付，基础设施按1年；PDF为主，DWG/DXF补充；人民币。
B3: 项目预算合计 | G3: =G30 -> 167055 | J3: 单图规范检查POC；不含学生评分、长期人工维护及销售利润。
B4: 研发交付月数 | D4: 4 | F4: 风险预备费率 | G4: 0.05
B5: 基础设施月数 | D5: 12 | J5: 一年设施费用不等于一年人工维护；详细单价说明见“单价依据与范围”。
B6: 成本类别 | C6: 费用项目 | D6: 数量 | E6: 单位 | F6: 单价（元） | G6: 金额（元） | J6: 数量、单价解释及范围
B7: 人力 | C7: 全栈工程师 × 1 | D7: =D4 -> 4 | E7: 人月 | F7: 25000 | G7: =IF(COUNT(D7,F7)<2,NA(),D7*F7) -> 100000 | J7: 4个月（3个月开发测试＋1个月演示试跑），25,000元/人月。
B8: 模型API | C8: Mistral OCR 4 | D8: 1 | E8: 项 | F8: =ROUNDUP(SUM(API测算!F8,API测算!H8)/100,0)*100 -> 100 | G8: =IF(COUNT(D8,F8)<2,NA(),D8*F8) -> 100 | J8: 开发与演示OCR费用，按100元纳入预算；实际调用推导见“API测算”。
C9: GPT-5.6 Sol | D9: 1 | E9: 项 | F9: =ROUNDUP(SUM(API测算!F9:F11,API测算!H9:H11)/100,0)*100 -> 11200 | G9: =IF(COUNT(D9,F9)<2,NA(),D9*F9) -> 11200 | J9: 视觉分析的图像、文字输入和计费输出，按100元取整纳入预算。
C10: GPT-6 Astra | D10: 1 | E10: 项 | F10: =API测算!F17+API测算!H17-F8-F9 -> 20600 | G10: =IF(COUNT(D10,F10)<2,NA(),D10*F10) -> 20600 | J10: 复杂问题审校的图像、文字输入和计费输出；承担API预算取整差额。
C11: 技术尽调验证 | D11: 1 | E11: 项 | F11: 0 | G11: =IF(COUNT(D11,F11)<2,NA(),D11*F11) -> 0 | J11: 签前用10张客户真实图纸验证完整链路；工程工时已含人力，不重复计费。
B12: 基础设施 | C12: 国内ECS实例 | D12: =$D$5 -> 12 | E12: 月 | F12: 450 | G12: =IF(COUNT(D12,F12)<2,NA(),D12*F12) -> 5400 | J12: 1台4核16G，计算资源约400元/月＋系统盘约50元/月。
C13: 国内公网带宽 | D13: =$D$5 -> 12 | E13: 月 | F13: 150 | G13: =IF(COUNT(D13,F13)<2,NA(),D13*F13) -> 1800 | J13: 公网访问预算150元/月，用于客户远程访问演示系统。
C14: 对象存储OSS | D14: 1 | E14: 年 | F14: 500 | G14: =IF(COUNT(D14,F14)<2,NA(),D14*F14) -> 500 | J14: 原图、切片与结果JSON存储，以及少量外网流量预留。
C15: 域名＋HTTPS证书 | D15: 1 | E15: 年 | F15: 300 | G15: =IF(COUNT(D15,F15)<2,NA(),D15*F15) -> 300 | J15: 域名及HTTPS证书年度预算。
C16: 云监控／日志／CI | D16: 1 | E16: 年 | F16: 1200 | G16: =IF(COUNT(D16,F16)<2,NA(),D16*F16) -> 1200 | J16: 告警、日志和持续集成流水线年度预算。
C17: 海外网关节点 | D17: =$D$5 -> 12 | E17: 月 | F17: 1500 | G17: =IF(COUNT(D17,F17)<2,NA(),D17*F17) -> 18000 | J17: 稳定接入节点及流量预算；不重复计模型token费用。
B18: 知识库 | C18: 国标文本资料 | D18: 30 | E18: 份 | F18: 0 | G18: =IF(COUNT(D18,F18)<2,NA(),D18*F18) -> 0 | J18: 客户提供所需标准资料；研发费用0元。
C19: 标准条款结构化 | D19: 1 | E19: 项 | F19: 0 | G19: =IF(COUNT(D19,F19)<2,NA(),D19*F19) -> 0 | J19: 客户机械顾问确定条款范围；研发结构化和工程实现已含研发人力。
C20: 专家规则转写 | D20: 1 | E20: 项 | F20: 0 | G20: =IF(COUNT(D20,F20)<2,NA(),D20*F20) -> 0 | J20: 客户专家提供并审核规则；研发转录开发已含研发人力。
C21: 向量库／图谱工具 | D21: 1 | E21: 项 | F21: 0 | G21: =IF(COUNT(D21,F21)<2,NA(),D21*F21) -> 0 | J21: 采用开源组件部署，无额外软件授权费用。
B22: 数据准备 | C22: 图纸样本收集 | D22: 1 | E22: 项 | F22: 0 | G22: =IF(COUNT(D22,F22)<2,NA(),D22*F22) -> 0 | J22: 客户负责收集、清理并提供轴类、箱体、钣金等典型图纸；研发费用0元。研发人员的数据接收和导入工作已含研发人力。
C23: 开发期人工标注 | D23: 30 | E23: 张 | F23: 0 | G23: =IF(COUNT(D23,F23)<2,NA(),D23*F23) -> 0 | J23: 客户专家负责问题判断、位置、依据和复核；属于客户承担的专家支持费用，研发费用0元。研发人员仅负责数据导入和联调，已含研发人力。
C24: 演示期补充标注 | D24: 20 | E24: 张 | F24: 0 | G24: =IF(COUNT(D24,F24)<2,NA(),D24*F24) -> 0 | J24: 客户专家负责演示样本的补充标注与复核；属于客户承担的专家支持费用，研发费用0元。
C25: 独立测试集标注 | D25: 20 | E25: 张 | F25: 0 | G25: =IF(COUNT(D25,F25)<2,NA(),D25*F25) -> 0 | J25: 客户专家独立完成留出测试集标注与复核；属于客户承担的专家支持费用，研发费用0元。
B26: 测评 | C26: 评估脚本／POC测试报告 | D26: 1 | E26: 项 | F26: 0 | G26: =IF(COUNT(D26,F26)<2,NA(),D26*F26) -> 0 | J26: 评估脚本、指标统计和POC报告已含人力。
B28: 直接费用小计 | G28: =SUM(G7:G26) -> 159100 | J28: API按官方费率和用量假设测算，其余费用为内部预算。
B29: 其他 | C29: 差旅、税费、不可预见 | G29: =G28*$G$4 -> 7955 | J29: 按直接费用×5%计提；不是税率或供应商服务费。
B30: 总计 | G30: =SUM(G28:G29) -> 167055
B33: 待确认增项（未计入合计） | J33: 专家由客户组织，属于客户承担的专家支持费用，不计入研发费用；这里只保留可能发生的CAD工具授权。
B35: CAD工具授权 | D35: 1 | E35: 项 | F35: 5000 | G35: =D35*F35 -> 5000 | J35: 5000元是采购预留上限假设，并非已取得的商用SDK授权报价。
B37: 计入CAD授权后的预算 | G37: =(G28+G35)*(1+$G$4) -> 172305 | J37: 如需购买CAD工具授权，追加直接费用后统一计提相同预备费率。
B40: 单价来源 | J40: 《研发成本估算.md》、示例CSV及官方API定价；未询价项目在单价说明表标记。
B41: 使用说明 | J41: 黄色蓝字可修改；黑字为计算值，绿字为跨表引用。
B42: 成本边界 | J42: 内部成本规划，非含税销售报价；不计第二阶段开发。
